toolgui/Roboto-Regular.ttf
toolgui/__init__.py
toolgui/_app.py
toolgui/_data.py
toolgui/_gui.py
toolgui-0.0.10.dist-info/METADATA
toolgui-0.0.10.dist-info/WHEEL
toolgui-0.0.10.dist-info/top_level.txt
toolgui-0.0.10.dist-info/RECORD
