Metadata-Version: 2.1
Name: toolgui
Version: 0.0.10
Summary: Modular event-driven GUI system for quickly building tools with Python and pyimgui.
Home-page: https://github.com/rempelj/toolgui
Author: Justin Rempel
License: UNKNOWN
Platform: UNKNOWN
Requires-Dist: imgui[glfw]
Provides-Extra: dev
Requires-Dist: twine ; extra == 'dev'
Requires-Dist: wheel ; extra == 'dev'
